MANIFEST.in
setup.cfg
setup.py
version.py
src/cgcloud/__init__.py
src/cgcloud/agent/__init__.py
src/cgcloud/agent/cli.py
src/cgcloud/agent/init-script.lsb
src/cgcloud/agent/init-script.systemd
src/cgcloud/agent/init-script.upstart
src/cgcloud_agent.egg-info/PKG-INFO
src/cgcloud_agent.egg-info/SOURCES.txt
src/cgcloud_agent.egg-info/dependency_links.txt
src/cgcloud_agent.egg-info/entry_points.txt
src/cgcloud_agent.egg-info/namespace_packages.txt
src/cgcloud_agent.egg-info/requires.txt
src/cgcloud_agent.egg-info/top_level.txt