Metadata-Version: 1.0
Name: cgcloud-agent
Version: 1.3a1.dev192
Summary: Management of ~/.ssh/authorized_keys for a fleet of EC2 instances
Home-page: https://github.com/BD2KGenomics/cgcloud
Author: Hannes Schmidt
Author-email: hannes@ucsc.edu
License: UNKNOWN
Platform: UNKNOWN
